{"nodes": [{"id": "horace"}, {"id": "dame"}, {"id": "congratulations"}, {"id": "greatest"}, {"id": "dum"}, {"id": "fiti"}, {"id": "te"}, {"id": "hail"}, {"id": "barn"}, {"id": "clayton"}, {"id": "ugh"}, {"id": "sea"}, {"id": "sky"}, {"id": "marlin"}, {"id": "explorer"}, {"id": "bianca"}, {"id": "unbirthday"}, {"id": "kanga"}, {"id": "mountains"}, {"id": "agent"}, {"id": "hakuna"}, {"id": "ba"}, {"id": "hours"}, {"id": "pancake"}, {"id": "sounds"}, {"id": "tuck"}, {"id": "grace"}, {"id": "bell"}, {"id": "owl"}, {"id": "dee"}, {"id": "brave"}, {"id": "wood"}, {"id": "bambi"}, {"id": "least"}, {"id": "pinoke"}, {"id": "oozma"}, {"id": "gentlemen"}, {"id": "snow"}, {"id": "khan"}, {"id": "zazu"}, {"id": "lads"}, {"id": "imelda"}, {"id": "jumbo"}, {"id": "headed"}, {"id": "favorite"}, {"id": "nemo"}, {"id": "acorn"}, {"id": "settle"}, {"id": "smee"}, {"id": "week"}, {"id": "painting"}, {"id": "michael"}, {"id": "oooroo"}, {"id": "leader"}, {"id": "radiator"}, {"id": "red"}, {"id": "actor"}, {"id": "corner"}, {"id": "robots"}, {"id": "seven"}, {"id": "hood"}, {"id": "mack"}, {"id": "tee"}, {"id": "da"}, {"id": "impressive"}, {"id": "wheel"}, {"id": "bare"}, {"id": "tip"}, {"id": "ground"}, {"id": "two"}, {"id": "naveen"}, {"id": "queen"}, {"id": "gosh"}, {"id": "year"}, {"id": "hike"}, {"id": "sally"}, {"id": "ernesto"}, {"id": "hana"}, {"id": "de"}, {"id": "shucks"}, {"id": "morph"}, {"id": "nose"}, {"id": "gon"}, {"id": "beloved"}, {"id": "incredible"}, {"id": "calm"}, {"id": "invited"}, {"id": "princess"}, {"id": "merry"}, {"id": "staring"}, {"id": "pigeon"}, {"id": "doomed"}, {"id": "goodness"}, {"id": "roses"}, {"id": "joe"}, {"id": "wan"}, {"id": "bay"}, {"id": "ew"}, {"id": "steering"}, {"id": "ayuk"}, {"id": "madam"}, {"id": "gotcha"}, {"id": "aladar"}, {"id": "ganda"}, {"id": "degrees"}, {"id": "guide"}, {"id": "hans"}, {"id": "ay"}, {"id": "mouth"}, {"id": "oodelally"}, {"id": "violet"}, {"id": "hundred"}, {"id": "buster"}, {"id": "fella"}, {"id": "pooh"}, {"id": "harder"}, {"id": "clothes"}, {"id": "shoo"}, {"id": "arrived"}, {"id": "toulouse"}, {"id": "jewel"}, {"id": "seconds"}, {"id": "robin"}, {"id": "stuffed"}, {"id": "pardon"}, {"id": "nine"}, {"id": "woof"}, {"id": "accident"}, {"id": "excited"}, {"id": "ichabod"}, {"id": "bing"}, {"id": "decide"}, {"id": "five"}, {"id": "hip"}, {"id": "favourite"}, {"id": "roo"}, {"id": "weeks"}, {"id": "friar"}, {"id": "charlie"}, {"id": "beam"}, {"id": "howdy"}, {"id": "wilderness"}, {"id": "yoohoo"}, {"id": "four"}, {"id": "acre"}, {"id": "toad"}, {"id": "bells"}, {"id": "necessities"}, {"id": "hooray"}, {"id": "stick"}, {"id": "expert"}, {"id": "worse"}, {"id": "wen"}, {"id": "rider"}, {"id": "kevin"}, {"id": "peter"}, {"id": "coco"}, {"id": "claws"}, {"id": "stickers"}, {"id": "mi"}, {"id": "whew"}, {"id": "um"}, {"id": "frankie"}, {"id": "enemy"}, {"id": "minutes"}, {"id": "bugsy"}, {"id": "gracious"}, {"id": "fellas"}, {"id": "catching"}, {"id": "shere"}, {"id": "pig"}, {"id": "allow"}, {"id": "ebay"}, {"id": "lool"}, {"id": "whoops"}, {"id": "sort"}, {"id": "cruella"}, {"id": "majesty"}, {"id": "hup"}, {"id": "christopher"}, {"id": "drop"}, {"id": "eeyore"}, {"id": "uh"}, {"id": "aaah"}, {"id": "ranjan"}, {"id": "atta"}, {"id": "rocket"}, {"id": "three"}, {"id": "health"}, {"id": "worried"}, {"id": "souls"}, {"id": "cup"}, {"id": "rogue"}, {"id": "future"}, {"id": "pige"}, {"id": "scar"}, {"id": "lips"}, {"id": "rose"}, {"id": "bong"}, {"id": "looks"}, {"id": "hmph"}, {"id": "talkin"}, {"id": "notre"}, {"id": "shower"}, {"id": "sydney"}, {"id": "kappa"}, {"id": "slink"}, {"id": "britches"}, {"id": "russell"}, {"id": "hat"}, {"id": "keeper"}, {"id": "cups"}, {"id": "expedition"}, {"id": "ladies"}, {"id": "mr"}, {"id": "mim"}, {"id": "highness"}, {"id": "jiminy"}, {"id": "heading"}, {"id": "flo"}, {"id": "drip"}, {"id": "stare"}, {"id": "ho"}, {"id": "jenny"}, {"id": "restore"}, {"id": "pan"}, {"id": "forgive"}, {"id": "sunday"}, {"id": "sandy"}, {"id": "meets"}, {"id": "barbie"}, {"id": "hen"}, {"id": "roger"}, {"id": "ellie"}, {"id": "jasper"}, {"id": "byebye"}, {"id": "hiya"}, {"id": "talking"}, {"id": "ten"}, {"id": "wind"}, {"id": "mana"}, {"id": "mrs"}, {"id": "homing"}, {"id": "kind"}, {"id": "al"}, {"id": "laser"}, {"id": "caw"}, {"id": "eight"}, {"id": "clever"}, {"id": "cruz"}, {"id": "aurora"}, {"id": "sherman"}, {"id": "oof"}, {"id": "excuse"}, {"id": "dot"}, {"id": "matata"}, {"id": "piston"}, {"id": "gift"}, {"id": "golly"}, {"id": "months"}, {"id": "emergency"}, {"id": "springs"}, {"id": "felix"}, {"id": "pow"}, {"id": "kittens"}, {"id": "fluff"}, {"id": "hearts"}, {"id": "fixit"}, {"id": "worries"}, {"id": "phillip"}, {"id": "marvelous"}, {"id": "piglet"}, {"id": "la"}, {"id": "biggest"}, {"id": "tinker"}, {"id": "less"}, {"id": "winnie"}, {"id": "six"}, {"id": "yah"}], "links": [{"source": "dum", "target": "da", "value": 0.730470597743988}, {"source": "dum", "target": "ba", "value": 0.7966633439064026}, {"source": "dum", "target": "tee", "value": 0.7848672866821289}, {"source": "dum", "target": "dee", "value": 0.815071702003479}, {"source": "wood", "target": "acre", "value": 0.8534220457077026}, {"source": "radiator", "target": "springs", "value": 0.7637059688568115}, {"source": "seven", "target": "ten", "value": 0.7479687333106995}, {"source": "seven", "target": "six", "value": 0.8377323746681213}, {"source": "seven", "target": "cups", "value": 0.7627242803573608}, {"source": "seven", "target": "nine", "value": 0.7696849703788757}, {"source": "seven", "target": "five", "value": 0.7258512377738953}, {"source": "seven", "target": "eight", "value": 0.8366225361824036}, {"source": "wheel", "target": "steering", "value": 0.7545233368873596}, {"source": "year", "target": "week", "value": 0.7272045016288757}, {"source": "nose", "target": "mouth", "value": 0.707692563533783}, {"source": "ew", "target": "yah", "value": 0.7071661353111267}, {"source": "ew", "target": "oooroo", "value": 0.7085395455360413}, {"source": "ew", "target": "pancake", "value": 0.730935275554657}, {"source": "guide", "target": "decide", "value": 0.7011722922325134}, {"source": "hundred", "target": "acre", "value": 0.7450271248817444}, {"source": "arrived", "target": "future", "value": 0.7989862561225891}, {"source": "woof", "target": "pancake", "value": 0.7235193848609924}, {"source": "woof", "target": "caw", "value": 0.7747341990470886}, {"source": "wen", "target": "hen", "value": 0.8433870077133179}, {"source": "enemy", "target": "leader", "value": 0.7080723643302917}, {"source": "drip", "target": "shower", "value": 0.9218714237213135}, {"source": "drip", "target": "drop", "value": 0.7592204213142395}, {"source": "ho", "target": "expedition", "value": 0.8364619016647339}, {"source": "restore", "target": "fiti", "value": 0.8755045533180237}, {"source": "restore", "target": "te", "value": 0.8686766028404236}, {"source": "ugh", "target": "hike", "value": 0.8953378796577454}, {"source": "impressive", "target": "clever", "value": 0.7133451700210571}, {"source": "naveen", "target": "phillip", "value": 0.729985773563385}, {"source": "naveen", "target": "hans", "value": 0.7881130576133728}, {"source": "violet", "target": "stickers", "value": 0.7182285189628601}, {"source": "violet", "target": "buster", "value": 0.7096232771873474}, {"source": "highness", "target": "majesty", "value": 0.8610488772392273}, {"source": "highness", "target": "grace", "value": 0.7275704741477966}, {"source": "clever", "target": "brave", "value": 0.7175455093383789}, {"source": "felix", "target": "fixit", "value": 0.7796987295150757}, {"source": "roses", "target": "painting", "value": 0.932409405708313}, {"source": "roses", "target": "red", "value": 0.7637807130813599}, {"source": "ay", "target": "mi", "value": 0.7879266738891602}, {"source": "harder", "target": "less", "value": 0.7017268538475037}, {"source": "harder", "target": "worse", "value": 0.7146205902099609}, {"source": "favourite", "target": "favorite", "value": 0.7135487198829651}, {"source": "gracious", "target": "gosh", "value": 0.7459976077079773}, {"source": "gracious", "target": "goodness", "value": 0.7206982374191284}, {"source": "lool", "target": "stare", "value": 0.7885987758636475}, {"source": "lool", "target": "flo", "value": 0.7200573682785034}, {"source": "majesty", "target": "grace", "value": 0.7892239689826965}, {"source": "pige", "target": "morph", "value": 0.7287346124649048}, {"source": "pige", "target": "stickers", "value": 0.7076596021652222}, {"source": "pige", "target": "rider", "value": 0.7154463529586792}, {"source": "pige", "target": "buster", "value": 0.706581711769104}, {"source": "ten", "target": "six", "value": 0.7939662337303162}, {"source": "ten", "target": "cups", "value": 0.7210292816162109}, {"source": "ten", "target": "nine", "value": 0.737553060054779}, {"source": "ten", "target": "five", "value": 0.8038408160209656}, {"source": "ten", "target": "eight", "value": 0.7837539315223694}, {"source": "ten", "target": "months", "value": 0.7261747121810913}, {"source": "ten", "target": "minutes", "value": 0.7836254835128784}, {"source": "kittens", "target": "mrs", "value": 0.7245404720306396}, {"source": "kittens", "target": "caw", "value": 0.7069372534751892}, {"source": "la", "target": "de", "value": 0.7014056444168091}, {"source": "yah", "target": "oof", "value": 0.7390607595443726}, {"source": "yah", "target": "aaah", "value": 0.742091953754425}, {"source": "yah", "target": "yoohoo", "value": 0.7293965816497803}, {"source": "yah", "target": "ayuk", "value": 0.840916633605957}, {"source": "unbirthday", "target": "merry", "value": 0.766974687576294}, {"source": "bambi", "target": "russell", "value": 0.7106263041496277}, {"source": "bambi", "target": "buster", "value": 0.7060844302177429}, {"source": "zazu", "target": "scar", "value": 0.700756311416626}, {"source": "lads", "target": "russell", "value": 0.705743670463562}, {"source": "morph", "target": "stickers", "value": 0.7668054103851318}, {"source": "morph", "target": "barbie", "value": 0.7152937650680542}, {"source": "morph", "target": "aladar", "value": 0.7562811970710754}, {"source": "morph", "target": "hiya", "value": 0.7534536719322205}, {"source": "morph", "target": "yoohoo", "value": 0.7006363272666931}, {"source": "morph", "target": "buster", "value": 0.7518054842948914}, {"source": "morph", "target": "bugsy", "value": 0.7306671142578125}, {"source": "madam", "target": "mim", "value": 0.7465988993644714}, {"source": "accident", "target": "acorn", "value": 0.7052306532859802}, {"source": "friar", "target": "russell", "value": 0.736512303352356}, {"source": "friar", "target": "tuck", "value": 0.8446810841560364}, {"source": "kevin", "target": "bugsy", "value": 0.7324607372283936}, {"source": "peter", "target": "pan", "value": 0.7586516737937927}, {"source": "aurora", "target": "queen", "value": 0.7312297224998474}, {"source": "aurora", "target": "health", "value": 0.7117342352867126}, {"source": "aurora", "target": "princess", "value": 0.7379677295684814}, {"source": "aurora", "target": "atta", "value": 0.7436292767524719}, {"source": "aurora", "target": "hail", "value": 0.8734434247016907}, {"source": "oof", "target": "ayuk", "value": 0.7867221832275391}, {"source": "bianca", "target": "sally", "value": 0.7179532051086426}, {"source": "hakuna", "target": "matata", "value": 0.9976916909217834}, {"source": "oozma", "target": "kappa", "value": 0.9740725755691528}, {"source": "da", "target": "ba", "value": 0.775093674659729}, {"source": "wan", "target": "gon", "value": 0.7195610404014587}, {"source": "gotcha", "target": "hiya", "value": 0.7507951855659485}, {"source": "roo", "target": "kanga", "value": 0.7447431087493896}, {"source": "howdy", "target": "hiya", "value": 0.7370408177375793}, {"source": "howdy", "target": "caw", "value": 0.7174805998802185}, {"source": "necessities", "target": "worries", "value": 0.7974667549133301}, {"source": "necessities", "target": "bare", "value": 0.9900263547897339}, {"source": "stickers", "target": "frankie", "value": 0.7471330761909485}, {"source": "stickers", "target": "bugsy", "value": 0.715846598148346}, {"source": "notre", "target": "dame", "value": 0.9644719362258911}, {"source": "notre", "target": "bells", "value": 0.7941203713417053}, {"source": "ellie", "target": "bugsy", "value": 0.7181839346885681}, {"source": "mana", "target": "hana", "value": 0.9981978535652161}, {"source": "mana", "target": "ganda", "value": 0.9988020658493042}, {"source": "worries", "target": "bare", "value": 0.8009521961212158}, {"source": "six", "target": "cups", "value": 0.7248888611793518}, {"source": "six", "target": "nine", "value": 0.7721940279006958}, {"source": "six", "target": "five", "value": 0.7963947653770447}, {"source": "six", "target": "eight", "value": 0.8143469095230103}, {"source": "six", "target": "months", "value": 0.7834656834602356}, {"source": "six", "target": "minutes", "value": 0.7299066781997681}, {"source": "horace", "target": "jasper", "value": 0.7101633548736572}, {"source": "dame", "target": "bells", "value": 0.8057628870010376}, {"source": "congratulations", "target": "hiya", "value": 0.7338977456092834}, {"source": "marlin", "target": "nemo", "value": 0.7449636459350586}, {"source": "hours", "target": "five", "value": 0.7176578640937805}, {"source": "hours", "target": "seconds", "value": 0.7167863249778748}, {"source": "hours", "target": "months", "value": 0.7315775752067566}, {"source": "hours", "target": "minutes", "value": 0.7494818568229675}, {"source": "bell", "target": "tinker", "value": 0.8105767369270325}, {"source": "snow", "target": "mountains", "value": 0.7305703163146973}, {"source": "settle", "target": "calm", "value": 0.7204537391662598}, {"source": "actor", "target": "dee", "value": 0.8039711117744446}, {"source": "tip", "target": "hat", "value": 0.7077394127845764}, {"source": "de", "target": "cruz", "value": 0.7983720898628235}, {"source": "de", "target": "ernesto", "value": 0.801736056804657}, {"source": "staring", "target": "stare", "value": 0.7566092014312744}, {"source": "doomed", "target": "invited", "value": 0.7296979427337646}, {"source": "excited", "target": "worried", "value": 0.7129718661308289}, {"source": "rider", "target": "ebay", "value": 0.7015235424041748}, {"source": "rider", "target": "aladar", "value": 0.7293975949287415}, {"source": "rider", "target": "yoohoo", "value": 0.7131657004356384}, {"source": "um", "target": "uh", "value": 0.7154645323753357}, {"source": "souls", "target": "hearts", "value": 0.7057907581329346}, {"source": "cups", "target": "nine", "value": 0.7687839269638062}, {"source": "cups", "target": "eight", "value": 0.7177421450614929}, {"source": "cups", "target": "three", "value": 0.7191550135612488}, {"source": "jiminy", "target": "whew", "value": 0.7244774699211121}, {"source": "cruz", "target": "ernesto", "value": 0.7532258629798889}, {"source": "excuse", "target": "forgive", "value": 0.7690632939338684}, {"source": "excuse", "target": "pardon", "value": 0.7625569105148315}, {"source": "barn", "target": "al", "value": 0.7129043340682983}, {"source": "sounds", "target": "looks", "value": 0.8005533814430237}, {"source": "painting", "target": "red", "value": 0.736151397228241}, {"source": "corner", "target": "stick", "value": 0.7265332937240601}, {"source": "four", "target": "five", "value": 0.7020400166511536}, {"source": "four", "target": "three", "value": 0.8309076428413391}, {"source": "four", "target": "hup", "value": 0.7243151664733887}, {"source": "four", "target": "degrees", "value": 0.7125667929649353}, {"source": "sunday", "target": "clothes", "value": 0.7911800742149353}, {"source": "laser", "target": "beam", "value": 0.7151035070419312}, {"source": "piston", "target": "cup", "value": 0.7764148712158203}, {"source": "fluff", "target": "winnie", "value": 0.727702796459198}, {"source": "marvelous", "target": "mim", "value": 0.7167565226554871}, {"source": "robots", "target": "rogue", "value": 0.7884812951087952}, {"source": "robots", "target": "caw", "value": 0.7267670631408691}, {"source": "queen", "target": "princess", "value": 0.7114734053611755}, {"source": "hana", "target": "ganda", "value": 0.9967541098594666}, {"source": "joe", "target": "bugsy", "value": 0.7220026850700378}, {"source": "joe", "target": "scar", "value": 0.7303122282028198}, {"source": "toulouse", "target": "aladar", "value": 0.7196053862571716}, {"source": "toulouse", "target": "shoo", "value": 0.7328795790672302}, {"source": "stuffed", "target": "winnie", "value": 0.7508898377418518}, {"source": "nine", "target": "five", "value": 0.7027180194854736}, {"source": "nine", "target": "eight", "value": 0.7819828391075134}, {"source": "weeks", "target": "five", "value": 0.715779185295105}, {"source": "weeks", "target": "seconds", "value": 0.7428514361381531}, {"source": "weeks", "target": "months", "value": 0.7704692482948303}, {"source": "weeks", "target": "minutes", "value": 0.769828200340271}, {"source": "toad", "target": "ichabod", "value": 0.721366286277771}, {"source": "fellas", "target": "buster", "value": 0.7170794010162354}, {"source": "catching", "target": "pow", "value": 0.7437799572944641}, {"source": "jenny", "target": "charlie", "value": 0.7150545716285706}, {"source": "forgive", "target": "pardon", "value": 0.7469043135643005}, {"source": "forgive", "target": "allow", "value": 0.7006776332855225}, {"source": "homing", "target": "pigeon", "value": 0.7061614394187927}, {"source": "sea", "target": "meets", "value": 0.7019195556640625}, {"source": "smee", "target": "clayton", "value": 0.7121254205703735}, {"source": "smee", "target": "mr", "value": 0.7464225888252258}, {"source": "beloved", "target": "gift", "value": 0.7075554728507996}, {"source": "oodelally", "target": "golly", "value": 0.8969260454177856}, {"source": "robin", "target": "hood", "value": 0.7351999282836914}, {"source": "robin", "target": "christopher", "value": 0.8863356113433838}, {"source": "five", "target": "eight", "value": 0.768070638179779}, {"source": "five", "target": "seconds", "value": 0.7670800089836121}, {"source": "five", "target": "three", "value": 0.7496312856674194}, {"source": "five", "target": "months", "value": 0.7315400242805481}, {"source": "five", "target": "minutes", "value": 0.8392835855484009}, {"source": "cruella", "target": "roger", "value": 0.7969348430633545}, {"source": "lips", "target": "rose", "value": 0.7070292234420776}, {"source": "sydney", "target": "sherman", "value": 0.7816646099090576}, {"source": "slink", "target": "buster", "value": 0.7130845189094543}, {"source": "britches", "target": "fella", "value": 0.7761651873588562}, {"source": "keeper", "target": "pig", "value": 0.7012699842453003}, {"source": "talking", "target": "talkin", "value": 0.8140982389450073}, {"source": "piglet", "target": "owl", "value": 0.7317304015159607}, {"source": "agent", "target": "emergency", "value": 0.710131049156189}, {"source": "least", "target": "stare", "value": 0.7827283143997192}, {"source": "khan", "target": "shere", "value": 0.9409569501876831}, {"source": "hood", "target": "christopher", "value": 0.758385956287384}, {"source": "ground", "target": "mountains", "value": 0.7718941569328308}, {"source": "claws", "target": "sandy", "value": 0.834404706954956}, {"source": "sort", "target": "kind", "value": 0.7774416208267212}, {"source": "biggest", "target": "greatest", "value": 0.7182976603507996}, {"source": "fiti", "target": "te", "value": 0.9524644613265991}, {"source": "imelda", "target": "coco", "value": 0.7385436296463013}, {"source": "two", "target": "three", "value": 0.7447341084480286}, {"source": "aladar", "target": "hiya", "value": 0.7051417827606201}, {"source": "aladar", "target": "yoohoo", "value": 0.7471158504486084}, {"source": "aladar", "target": "ayuk", "value": 0.7208282947540283}, {"source": "aladar", "target": "shoo", "value": 0.7334165573120117}, {"source": "aladar", "target": "bugsy", "value": 0.7430832386016846}, {"source": "whew", "target": "michael", "value": 0.7058166861534119}, {"source": "whew", "target": "dot", "value": 0.7058081030845642}, {"source": "whoops", "target": "ayuk", "value": 0.7034996151924133}, {"source": "aaah", "target": "yoohoo", "value": 0.7132803201675415}, {"source": "aaah", "target": "ayuk", "value": 0.8026001453399658}, {"source": "bong", "target": "bing", "value": 0.995691180229187}, {"source": "stare", "target": "flo", "value": 0.71979159116745}, {"source": "hiya", "target": "shucks", "value": 0.7174110412597656}, {"source": "hiya", "target": "ayuk", "value": 0.704943835735321}, {"source": "hiya", "target": "byebye", "value": 0.731632649898529}, {"source": "hiya", "target": "jumbo", "value": 0.7056288719177246}, {"source": "seconds", "target": "months", "value": 0.7065486311912537}, {"source": "seconds", "target": "minutes", "value": 0.8287709951400757}, {"source": "hip", "target": "hooray", "value": 0.8493269085884094}, {"source": "yoohoo", "target": "ayuk", "value": 0.8141723275184631}, {"source": "expert", "target": "emergency", "value": 0.7793238162994385}, {"source": "owl", "target": "eeyore", "value": 0.7009679675102234}, {"source": "headed", "target": "heading", "value": 0.7011709809303284}, {"source": "tee", "target": "dee", "value": 0.7492390275001526}, {"source": "bay", "target": "jewel", "value": 0.8098831176757812}, {"source": "ayuk", "target": "hmph", "value": 0.720349907875061}, {"source": "pooh", "target": "winnie", "value": 0.7333402037620544}, {"source": "ranjan", "target": "pinoke", "value": 0.7109964489936829}, {"source": "wind", "target": "sky", "value": 0.7140697836875916}, {"source": "mrs", "target": "jumbo", "value": 0.7292677760124207}, {"source": "mrs", "target": "buster", "value": 0.734859824180603}, {"source": "months", "target": "minutes", "value": 0.7257797718048096}, {"source": "pow", "target": "incredible", "value": 0.7857861518859863}, {"source": "explorer", "target": "wilderness", "value": 0.8006463050842285}, {"source": "kanga", "target": "eeyore", "value": 0.7454887628555298}, {"source": "mack", "target": "bugsy", "value": 0.7212029099464417}, {"source": "ladies", "target": "gentlemen", "value": 0.7574239373207092}, {"source": "caw", "target": "jumbo", "value": 0.7365634441375732}, {"source": "hooray", "target": "rocket", "value": 0.7095574140548706}]}